{
	"pageExperience": {
		"fieldData": {
			"lcp": {
				"unit": {
					"name": "s",
					"conversion": 1000
				},
				"data": {
					"numericValue": 3100,
					"score": 0.5166666666666667,
					"category": "AVERAGE"
				}
			},
			"fid": {
				"unit": {
					"name": "ms",
					"conversion": 1
				},
				"data": {
					"numericValue": 289,
					"score": 0.36125,
					"category": "AVERAGE"
				}
			},
			"cls": {
				"unit": {
					"name": "",
					"conversion": 100
				},
				"data": {
					"numericValue": 7,
					"score": 0.175,
					"category": "FAST"
				}
			}
		},
		"labData": {
			"lcp": {
				"unit": {
					"name": "s",
					"conversion": 1000
				},
				"data": {
					"numericValue": 3395.517406396801,
					"proportion": {
						"fast": 2500,
						"average": 4000,
						"slow": 6000
					},
					"category": "FAST"
				}
			},
			"fid": {
				"unit": {
					"name": "ms",
					"conversion": 1
				},
				"data": {
					"numericValue": 316.4999999999998,
					"proportion": {
						"fast": 100,
						"average": 300,
						"slow": 800
					},
					"category": "FAST"
				}
			},
			"cls": {
				"unit": {
					"name": "",
					"conversion": 100
				},
				"data": {
					"numericValue": 0,
					"proportion": {
						"fast": 10,
						"average": 25,
						"slow": 40
					},
					"category": "FAST"
				}
			}
		},
		"textCompression": true,
		"fastServerResponse": true,
		"usesAppropriatelySizedImages": true,
		"usesOptimizedImages": true,
		"usesWebpImages": true,
		"fastFontDisplay": true,
		"minifiedCss": true
	}
}
